register_file.sv
module register_file (input logic clk,
  input logic write_enable,
  input logic [2:0] write_addr, 
  input logic[15:0] write_data, 
  input logic [2:0] read_addr1, 
  input logic[2:0] read_addr2, 
  output logic[15:0] read_data1,
  output logic[15:0] read_data2,
  output logic [15:0] fib_out);


    logic [15:0] registers[7:0];

    //initializing the arr at the start of simulation

    initial begin

        for (int i = 0; i < 8; i++) begin
            registers[i] = 16'h0000;
        end

    end

    always_ff @(posedge clk) begin

        if (write_enable == 1) begin
            registers[write_addr] <= write_data;
        end

    end
    
    //if we read the same register we are currently writing to,
    //bypass the memory array and grab the "write_data" directly.

    //basically checks if the address we are tryna read  is the same as the address we are writing too right now.
    //and if it is, you just grab the data sitting on the write_data wire and pass it thru
    assign read_data1 = (write_enable && (read_addr1 == write_addr)) ? write_data : registers[read_addr1];
    assign read_data2 = (write_enable && (read_addr2 == write_addr)) ? write_data : registers[read_addr2];
    assign fib_out = registers[5];



endmodule

instruction_memory.sv
module instruction_memory(input logic[15:0] address_in, output logic[15:0] instruction_out);

    logic[15:0] addresses[255:0];

    `ifdef SIMULATION
    initial begin
        $readmemh("program.hex", addresses, 0, 255);
    end
    assign instruction_out = addresses[address_in[7:0]];
    `else
    //this is hardcoded for the fibonacci sequence, cuz readmemh might not work on an FPGA.
    always_comb begin
    case (address_in)
        16'h0000: instruction_out = 16'h6200;
        16'h0001: instruction_out = 16'h6401;
        16'h0002: instruction_out = 16'h6002;
        16'h0003: instruction_out = 16'h0A50;
        16'h0004: instruction_out = 16'h0280;
        16'h0005: instruction_out = 16'h0540;
        16'h0006: instruction_out = 16'h8005;
        default: instruction_out = 16'h0000;
    endcase
    end
    `endif

    

endmodule

data_memory.sv
module data_memory(
    input logic clk, 
    input logic reset, // Add reset here
    input logic write_enable, 
    input logic[15:0] write_addr, 
    input logic[15:0] write_data, 
    input logic[15:0] read_addr, 
    output logic[15:0] read_data
);

    logic [15:0] memory[255:0];

    // Remove the initial block completely

    always_ff @(posedge clk) begin
        if (reset) begin
            // Initialize your Fib starting values on reset
            memory[0] <= 16'd0;
            memory[1] <= 16'd1;
            memory[2] <= 16'd0;
        end else if (write_enable == 1) begin
            memory[write_addr[7:0]] <= write_data;
        end
    end

    assign read_data = memory[read_addr[7:0]];

endmodule

control_unit.sv
module control_unit(input logic[15:0] instruction, output logic[2:0] alu_op, output logic reg_write_enable, output logic mem_write_enable, output logic mem_read, output logic mem_to_reg, output logic branch, output logic halt, output logic alu_src);

    parameter addition = 4'b0000;
    parameter subtraction = 4'b0001;
    parameter and_op = 4'b0010;
    parameter or_op = 4'b0011;
    parameter shift_left = 4'b0100;
    parameter shift_right = 4'b0101;
    parameter load = 4'b0110;
    parameter store = 4'b0111;
    parameter beq = 4'b1000;
    parameter halt_op = 4'b1001;
    parameter xor_op = 4'b1010;
    parameter not_op = 4'b1011;

    logic [3:0] opcode;
    assign opcode = instruction[15:12];

    always_comb begin

        case (opcode)

            4'b0000: begin //ADDITION

            alu_op = 3'b000;
            reg_write_enable = 1;
            mem_write_enable = 0;
            mem_read = 0;
            mem_to_reg = 0; 
            branch = 0;
            halt = 0;
            alu_src = 0;

            end
            4'b0001: begin //SUBTRACTION

            alu_op = 3'b001;
            reg_write_enable = 1;
            mem_write_enable = 0;
            mem_read = 0;
            mem_to_reg = 0;
            branch = 0;
            halt = 0;
            alu_src = 0;

            end
            4'b0010: begin //AND

            alu_op = 3'b010;
            reg_write_enable = 1;
            mem_write_enable = 0;
            mem_read = 0;
            mem_to_reg = 0;
            branch = 0;
            halt = 0;
            alu_src = 0;

            end
            4'b0011: begin //OR

            alu_op = 3'b011;
            reg_write_enable = 1;
            mem_write_enable = 0;
            mem_read = 0;
            mem_to_reg = 0;
            branch = 0;
            halt = 0;
            alu_src = 0;
            
            end
            4'b0100: begin //SHIFT LEFT

            alu_op = 3'b100;
            reg_write_enable = 1;
            mem_write_enable = 0;
            mem_read = 0;
            mem_to_reg = 0;
            branch = 0;
            halt = 0;
            alu_src = 0;

            end
            4'b0101: begin //SHIFT RIGHT

            alu_op = 3'b101;
            reg_write_enable = 1;
            mem_write_enable = 0;
            mem_read = 0;
            mem_to_reg = 0; 
            branch = 0;
            halt = 0;
            alu_src = 0;

            end
            4'b0110: begin //LOAD

            alu_op = 3'b000; //add but acts as a placeholder doesn't do anything
            reg_write_enable = 1;
            mem_write_enable = 0;
            mem_read = 1;
            mem_to_reg = 1; 
            branch = 0;
            halt = 0;
            alu_src = 1;

            end
            4'b0111: begin //STORE

            alu_op = 3'b000; //add but acts as a placeholder doesn't do anything
            reg_write_enable = 0;
            mem_write_enable = 1;
            mem_read = 0;
            mem_to_reg = 0; 
            branch = 0;
            halt = 0;
            alu_src = 1;

            end
            4'b1000: begin //BEQ

            alu_op = 3'b001; //subtract
            reg_write_enable = 0;
            mem_write_enable = 0;
            mem_read = 0;
            mem_to_reg = 0;
            branch = 1;
            halt = 0;
            alu_src = 0;

            end
            4'b1001: begin //HALT

            alu_op = 3'b000; //add but acts as a placeholder doesn't do anything
            reg_write_enable = 0;
            mem_write_enable = 0;
            mem_read = 0;
            mem_to_reg = 0;
            branch = 0;
            halt = 1;
            alu_src = 0;

            end
            4'b1010: begin //XOR
            alu_op = 3'b110;
            reg_write_enable = 1;
            mem_write_enable = 0;
            mem_read = 0;
            mem_to_reg = 0;
            branch = 0;
            halt = 0;
            alu_src = 0;
            end
            4'b1011: begin //NOT
            alu_op = 3'b111;
            reg_write_enable = 1;
            mem_write_enable = 0;
            mem_read = 0;
            mem_to_reg = 0;
            branch = 0;
            halt = 0;
            alu_src = 0;
            end
            
            default: begin
                alu_op = 3'b000;
                reg_write_enable = 0;
                mem_write_enable = 0;
                mem_read = 0;
                mem_to_reg = 0;
                branch = 0;
                halt = 0;
                alu_src = 0;
            end
            

        endcase

    end

endmodule

alu.sv
module alu(input logic[15:0] x, input logic[15:0] y, input logic[2:0] operation, output logic[16:0] result, output logic zero_flag);

    parameter addition = 3'b000;
    parameter subtraction = 3'b001;
    parameter and_op = 3'b010;
    parameter or_op = 3'b011;
    parameter shift_left = 3'b100;
    parameter shift_right = 3'b101;
    parameter xor_op = 3'b110;
    parameter not_op = 3'b111;

    always_comb begin

        case (operation)

            3'b000: begin
                result = x + y;
            end
            3'b001: begin
                result = x - y;
            end
            3'b010: begin
                result = x & y;
            end
            3'b011: begin
                result = x | y;
            end
            3'b100: begin
                result = x << 1;
            end
            3'b101: begin
                result = x >> 1;
            end
            3'b110: begin
                result = (x & ~y) | (~x & y);
            end
            3'b111: begin
                result = ~x;
            end



        endcase

    end

    //checks if the last result was zero
    //needed for BEQ,
    assign zero_flag = (result[15:0] == 16'h0000);


endmodule

program_counter.sv
module program_counter(input logic branch, input logic[15:0] branch_addr, input logic pc_write_enable, input logic clk, input logic reset, output logic[15:0] pc_out);

always_ff @(posedge clk) begin
    if (reset == 1) begin
        pc_out <= 0;
    end
    else if(branch == 1) begin
        pc_out <= branch_addr;
    end
    //pc_write_enable is equal to not stalling so it checks if it wont stall before moving forward.
    else if (pc_write_enable) begin
        pc_out <= pc_out + 1;
    end

end

endmodule

forwarding_unit.sv
module forwarding_unit(
input logic[2:0] id_ex_read_addr1, 
input logic[2:0] id_ex_read_addr2,
input logic[2:0] ex_mem_write_addr, 
input logic ex_mem_reg_write_enable, 
input logic[2:0] mem_wb_write_addr, 
input logic mem_wb_reg_write_enable,
output logic[1:0] forward_a,
output logic[1:0] forward_b
);

    always_comb begin

        if (ex_mem_reg_write_enable == 1 && ex_mem_write_addr == id_ex_read_addr1) begin
            forward_a = 2'b10;
        end else if (mem_wb_reg_write_enable == 1 && mem_wb_write_addr == id_ex_read_addr1) begin
            forward_a = 2'b01;
        end else begin
            forward_a = 2'b00;
        end

        if (ex_mem_reg_write_enable == 1 && ex_mem_write_addr == id_ex_read_addr2) begin
            forward_b = 2'b10;
        end else if (mem_wb_reg_write_enable == 1 && mem_wb_write_addr == id_ex_read_addr2) begin
            forward_b = 2'b01;
        end else begin
            forward_b = 2'b00;
        end

    end



endmodule

cpu.sv
module cpu(input logic clk, input logic reset, output logic [15:0] result, output logic [15:0] fib_out);
    
    //fetch logic stuff
    logic[15:0] instruction;
    logic[15:0] pc_out;
    logic[15:0] if_id_instruction;
    logic[15:0] if_id_pc;

    //decode logic stuff
    logic[2:0] read_addr1;
    logic[2:0] read_addr2;
    
    
    assign read_addr1 = if_id_instruction[8:6];
    assign read_addr2 = if_id_instruction[5:3];

    logic[15:0] read_data1;
    logic[15:0] read_data2;
    logic[2:0] alu_op;
    logic alu_src;
    logic mem_write_enable;
    logic reg_write_enable;
    logic mem_read;
    logic mem_to_reg;
    logic branch;
    logic halt;
    logic[2:0] write_addr;
    logic[15:0] immediate;
    assign write_addr = if_id_instruction[11:9];

    //takes the 3rd bit of my instruction, repeats it five times, this way it can handle negative numbers
    assign immediate = {{13{if_id_instruction[2]}}, if_id_instruction[2:0]};
    
    logic[15:0] id_ex_read_data1;
    logic[15:0] id_ex_read_data2;
    logic[2:0] id_ex_alu_op;
    logic[2:0] id_ex_read_addr1;
    logic[2:0] id_ex_read_addr2;
    logic id_ex_alu_src;
    logic id_ex_reg_write_enable;
    logic id_ex_mem_write_enable;
    logic id_ex_mem_read;
    logic id_ex_mem_to_reg;
    logic id_ex_branch;
    logic id_ex_halt;
    logic[2:0] id_ex_write_addr;
    logic[15:0] id_ex_immediate;
    logic[15:0] id_ex_pc;

    //execute logic stuff
    logic[15:0] branch_addr;
    logic[16:0] alu_result;
    assign branch_addr = id_ex_pc + id_ex_immediate;

    logic zero_flag;
    logic actual_branch;
    assign actual_branch = id_ex_branch & zero_flag;

    logic[16:0] ex_mem_alu_result;
    logic[15:0] ex_mem_read_data2;
    logic[15:0] ex_mem_branch_addr;
    logic[2:0] ex_mem_write_addr;
    logic ex_mem_reg_write_enable;
    logic ex_mem_mem_write_enable;
    logic ex_mem_mem_read;
    logic ex_mem_mem_to_reg;
    logic ex_mem_branch;
    logic ex_mem_halt;
    
    //mem logic stuff

    logic[15:0] mem_read_data;
    
    logic[16:0] mem_wb_alu_result;
    logic[15:0] mem_wb_mem_read_data;
    logic[2:0] mem_wb_write_addr;
    logic mem_wb_mem_to_reg;
    logic mem_wb_reg_write_enable;

    //writeback logic stuff
    logic[15:0] write_back_data;

    //forwarding stuff
    logic[1:0] forward_a;
    logic[1:0] forward_b;
    logic[15:0] alu_input_a;
    logic[15:0] alu_input_b;

    

    assign alu_input_a = (forward_a == 2'b10) ? ex_mem_alu_result[15:0] :
                         (forward_a == 2'b01) ? write_back_data :
                         id_ex_read_data1;
    
    logic [15:0] forward_b_data;
    assign forward_b_data = (forward_b == 2'b10) ? ex_mem_alu_result[15:0] :
                         (forward_b == 2'b01) ? write_back_data :
                         id_ex_read_data2;
    assign alu_input_b = id_ex_alu_src ? id_ex_immediate : forward_b_data;
    

    forwarding_unit forward_inst (
        .id_ex_read_addr1(id_ex_read_addr1),
        .id_ex_read_addr2(id_ex_read_addr2),
        .ex_mem_write_addr(ex_mem_write_addr),
        .ex_mem_reg_write_enable(ex_mem_reg_write_enable),
        .mem_wb_write_addr(mem_wb_write_addr),
        .mem_wb_reg_write_enable(mem_wb_reg_write_enable),
        .forward_a(forward_a),
        .forward_b(forward_b)
    );
    

    //stall logic, if there is a hazard, checks if the instruction in the execute stage its tryna get data from memory, but also trying to access that memory simultaneously, then you halt, basically chill out for a sec 
    //waiting for the next clock so you can actually grab it! this prevents me from putting manual "NOP" commands between each assembly line
    logic stall;
    assign stall = id_ex_mem_read && ((id_ex_write_addr == read_addr1) || (id_ex_write_addr == read_addr2));
    


    //if id pipeline register --> sits between fetch and decode
    // holds the fetched instruction until decode stage reads it
    always_ff @(posedge clk) begin
        if (reset || ex_mem_branch) begin
            if_id_instruction <= 0;
            if_id_pc <= 0;
        //checks if its not stalling so it can then assign new instructions, and as such it'll hold the previous values until the next clock cycle.   
        end
        if (!stall) begin   
            if_id_instruction <= instruction;
            if_id_pc <= pc_out;
        end
    end

    //ID/EX pipeline register --> sits between decode and execute
    //holds decoded control signals and register values until execute reads them
    always_ff @(posedge clk) begin
        //if branch signal is high then u zero out everything here for make way for instructions comin from branch target
        if (reset || ex_mem_branch) begin
            id_ex_read_data1 <= 0;
            id_ex_read_data2 <= 0;
            id_ex_alu_op <= 0;
            id_ex_reg_write_enable <= 0;
            id_ex_mem_write_enable <= 0;
            id_ex_mem_read <= 0;
            id_ex_mem_to_reg <= 0;
            id_ex_branch <= 0;
            id_ex_halt <= 0;
            id_ex_write_addr <= 0;
            id_ex_immediate <= 0;
            id_ex_pc <= 0;
            id_ex_read_addr1 <= 0;
            id_ex_read_addr2 <= 0;
            id_ex_alu_src <= 0;
        end else begin
            id_ex_read_data1 <= read_data1;
            id_ex_read_data2 <= read_data2;
            id_ex_alu_op <= alu_op;
            //IF it is gonna stall, then just write 0, if not then continue on
            id_ex_reg_write_enable <= stall ? 1'b0 : reg_write_enable;
            //same here
            id_ex_mem_write_enable <= stall ? 1'b0 : mem_write_enable;
            //conditional check to prevent stalled instruction from triggering a "second" stall cycle.
            id_ex_mem_read <= stall ? 1'b0 : mem_read;
            id_ex_mem_to_reg <= mem_to_reg;
            //to prevent a "ghost" branch from occurring while the pipeline is paused.
            id_ex_branch <= stall ? 1'b0 : branch;
            id_ex_halt <= halt;
            id_ex_write_addr <= write_addr;
            id_ex_immediate <= immediate;
            id_ex_pc <= if_id_pc;
            id_ex_read_addr1 <= read_addr1;
            id_ex_read_addr2 <= read_addr2;
            id_ex_alu_src <= alu_src;
        end

    end

    //EX/MEM pipeline egister --> sits between execute and memory
    //holds ALU result and control signals until memory stage reads them
    always_ff @(posedge clk) begin
    
    if (reset) begin
        ex_mem_read_data2 <= 0;
        ex_mem_branch_addr <= 0;
        ex_mem_write_addr <= 0;
        ex_mem_reg_write_enable <= 0;
        ex_mem_mem_write_enable <= 0;
        ex_mem_mem_read <= 0;
        ex_mem_mem_to_reg <= 0;
        ex_mem_branch <= 0;
        ex_mem_halt <= 0;
        ex_mem_alu_result <= 0;
    end else begin
        ex_mem_read_data2 <= forward_b_data;
        ex_mem_branch_addr <= branch_addr;
        ex_mem_write_addr <= id_ex_write_addr;
        ex_mem_reg_write_enable <= id_ex_reg_write_enable;
        ex_mem_mem_write_enable <= id_ex_mem_write_enable;
        ex_mem_mem_read <= id_ex_mem_read;
        ex_mem_mem_to_reg <= id_ex_mem_to_reg;
        ex_mem_branch <= actual_branch;
        ex_mem_halt <= id_ex_halt;
        ex_mem_alu_result <= alu_result;

        
    end

    end

    //MEM/WB pipeline register --> sits between memory and wrieback
    //holds memory read data and ALU result until writeback reads it
    always_ff @(posedge clk) begin

        if (reset) begin
            mem_wb_alu_result <= 0;
            mem_wb_mem_read_data <= 0;
            mem_wb_write_addr <= 0;
            mem_wb_mem_to_reg <= 0;
            mem_wb_reg_write_enable <= 0;
        end else begin
            mem_wb_alu_result <= ex_mem_alu_result;
            mem_wb_mem_read_data <= mem_read_data;
            mem_wb_write_addr <= ex_mem_write_addr;
            mem_wb_mem_to_reg <= ex_mem_mem_to_reg;
            mem_wb_reg_write_enable <= ex_mem_reg_write_enable;
        end

    end

    //writeback stage --> no pipeline reg cuz it's the last stage
    // selects between memory read data (for LOAD) or ALU result and writes back to the register file
    //purely combinational
    assign write_back_data = mem_wb_mem_to_reg ? mem_wb_mem_read_data : mem_wb_alu_result[15:0];
    assign result = write_back_data;

    logic cpu_halted;
    logic pc_write_enable;
    //halt logic to actually stop the CPU
    always_ff @(posedge clk) begin
        if (reset) begin
            cpu_halted <= 0;
        end else if (ex_mem_halt) begin
            cpu_halted <= 1;
        end
    end
    //if not stalling and the cpu isnt halted then it can enable writing
    assign pc_write_enable = !stall && !cpu_halted;


    
    
    //instantiating the program counter
    program_counter pc (
        .clk(clk),
        .reset(reset),
        .pc_out(pc_out),
        .branch(ex_mem_branch),
        .branch_addr(ex_mem_branch_addr),
        .pc_write_enable(pc_write_enable)
        
    );

    //instantiating the alu
    alu alu_inst (
        .x(alu_input_a),
        .y(alu_input_b),
        .operation(id_ex_alu_op),
        .result(alu_result),
        .zero_flag(zero_flag)
    );

    //instantiating the control_unit
    control_unit control_unit_inst (
        .instruction(if_id_instruction),
        .alu_op(alu_op),
        .reg_write_enable(reg_write_enable),
        .mem_write_enable(mem_write_enable),
        .mem_read(mem_read),
        .mem_to_reg(mem_to_reg),
        .branch(branch),
        .halt(halt),
        .alu_src(alu_src)
    );

    //instantiating the data memory
    data_memory data_memory_inst (
        .clk(clk),
        .reset(reset), // Wire the reset signal here
        .write_enable(ex_mem_mem_write_enable),
        .write_addr(ex_mem_alu_result[15:0]),
        .write_data(ex_mem_read_data2),
        .read_addr(ex_mem_alu_result[15:0]),
        .read_data(mem_read_data)
    );

    //instantiating the instruction memory
    instruction_memory instruction_memory_inst (
        .address_in(pc_out),
        .instruction_out(instruction)
    );

    //instantiating the reg file
    register_file reg_file_inst(
        .clk(clk),
        .write_enable(mem_wb_reg_write_enable),
        .write_data(write_back_data),
        .write_addr(mem_wb_write_addr),
        .read_addr1(read_addr1),
        .read_addr2(read_addr2),
        .read_data1(read_data1),
        .read_data2(read_data2),
        .fib_out(fib_out)
    );



endmodule

cpu_tb.sv
module cpu_tb;

    logic clk;
    logic reset;
    logic [15:0] result;
    logic [15:0] fib_out;

    cpu uut(
        .clk(clk),
        .reset(reset),
        .result(result),
        .fib_out(fib_out)
    );

    always #1 clk = ~clk;

    initial begin
        clk = 0;
        reset = 1;
        #100;
        reset = 0;
        #500;
        $finish;
    end

    initial begin
        $dumpfile("cpu_tb.vcd");
        $dumpvars(0, cpu_tb);
    end

    initial begin
        wait(reset == 0); 
        repeat(5) @(posedge clk); 
    
        $display("NEW FIBONACCI FOUND:     0"); // The Seed from r1
        $display("NEW FIBONACCI FOUND:     1"); // The Seed from r2
    end

    always @(posedge clk) begin

    

        if (uut.reg_file_inst.write_enable && (uut.reg_file_inst.write_addr == 3'd5)) begin
            $display("NEW FIBONACCI FOUND: %d", uut.reg_file_inst.write_data);
        end

    end

    

endmodule

cpu_tb.vcd
$date
	Sun May  3 18:48:07 2026
$end
$version
	Icarus Verilog
$end
$timescale
	1s
$end
$scope module cpu_tb $end
$var wire 16 ! result [15:0] $end
$var wire 16 " fib_out [15:0] $end
$var reg 1 # clk $end
$var reg 1 $ reset $end
$scope module uut $end
$var wire 1 % actual_branch $end
$var wire 1 # clk $end
$var wire 1 & pc_write_enable $end
$var wire 1 $ reset $end
$var wire 16 ' result [15:0] $end
$var wire 1 ( stall $end
$var wire 1 ) zero_flag $end
$var wire 16 * write_back_data [15:0] $end
$var wire 3 + write_addr [2:0] $end
$var wire 1 , reg_write_enable $end
$var wire 16 - read_data2 [15:0] $end
$var wire 16 . read_data1 [15:0] $end
$var wire 3 / read_addr2 [2:0] $end
$var wire 3 0 read_addr1 [2:0] $end
$var wire 16 1 pc_out [15:0] $end
$var wire 1 2 mem_write_enable $end
$var wire 1 3 mem_to_reg $end
$var wire 16 4 mem_read_data [15:0] $end
$var wire 1 5 mem_read $end
$var wire 16 6 instruction [15:0] $end
$var wire 16 7 immediate [15:0] $end
$var wire 1 8 halt $end
$var wire 16 9 forward_b_data [15:0] $end
$var wire 2 : forward_b [1:0] $end
$var wire 2 ; forward_a [1:0] $end
$var wire 16 < fib_out [15:0] $end
$var wire 16 = branch_addr [15:0] $end
$var wire 1 > branch $end
$var wire 1 ? alu_src $end
$var wire 17 @ alu_result [16:0] $end
$var wire 3 A alu_op [2:0] $end
$var wire 16 B alu_input_b [15:0] $end
$var wire 16 C alu_input_a [15:0] $end
$var reg 1 D cpu_halted $end
$var reg 17 E ex_mem_alu_result [16:0] $end
$var reg 1 F ex_mem_branch $end
$var reg 16 G ex_mem_branch_addr [15:0] $end
$var reg 1 H ex_mem_halt $end
$var reg 1 I ex_mem_mem_read $end
$var reg 1 J ex_mem_mem_to_reg $end
$var reg 1 K ex_mem_mem_write_enable $end
$var reg 16 L ex_mem_read_data2 [15:0] $end
$var reg 1 M ex_mem_reg_write_enable $end
$var reg 3 N ex_mem_write_addr [2:0] $end
$var reg 3 O id_ex_alu_op [2:0] $end
$var reg 1 P id_ex_alu_src $end
$var reg 1 Q id_ex_branch $end
$var reg 1 R id_ex_halt $end
$var reg 16 S id_ex_immediate [15:0] $end
$var reg 1 T id_ex_mem_read $end
$var reg 1 U id_ex_mem_to_reg $end
$var reg 1 V id_ex_mem_write_enable $end
$var reg 16 W id_ex_pc [15:0] $end
$var reg 3 X id_ex_read_addr1 [2:0] $end
$var reg 3 Y id_ex_read_addr2 [2:0] $end
$var reg 16 Z id_ex_read_data1 [15:0] $end
$var reg 16 [ id_ex_read_data2 [15:0] $end
$var reg 1 \ id_ex_reg_write_enable $end
$var reg 3 ] id_ex_write_addr [2:0] $end
$var reg 16 ^ if_id_instruction [15:0] $end
$var reg 16 _ if_id_pc [15:0] $end
$var reg 17 ` mem_wb_alu_result [16:0] $end
$var reg 16 a mem_wb_mem_read_data [15:0] $end
$var reg 1 b mem_wb_mem_to_reg $end
$var reg 1 c mem_wb_reg_write_enable $end
$var reg 3 d mem_wb_write_addr [2:0] $end
$scope module alu_inst $end
$var wire 3 e operation [2:0] $end
$var wire 16 f x [15:0] $end
$var wire 16 g y [15:0] $end
$var wire 1 ) zero_flag $end
$var parameter 3 h addition $end
$var parameter 3 i and_op $end
$var parameter 3 j not_op $end
$var parameter 3 k or_op $end
$var parameter 3 l shift_left $end
$var parameter 3 m shift_right $end
$var parameter 3 n subtraction $end
$var parameter 3 o xor_op $end
$var reg 17 p result [16:0] $end
$upscope $end
$scope module control_unit_inst $end
$var wire 16 q instruction [15:0] $end
$var wire 4 r opcode [3:0] $end
$var parameter 4 s addition $end
$var parameter 4 t and_op $end
$var parameter 4 u beq $end
$var parameter 4 v halt_op $end
$var parameter 4 w load $end
$var parameter 4 x not_op $end
$var parameter 4 y or_op $end
$var parameter 4 z shift_left $end
$var parameter 4 { shift_right $end
$var parameter 4 | store $end
$var parameter 4 } subtraction $end
$var parameter 4 ~ xor_op $end
$var reg 3 !" alu_op [2:0] $end
$var reg 1 ? alu_src $end
$var reg 1 > branch $end
$var reg 1 8 halt $end
$var reg 1 5 mem_read $end
$var reg 1 3 mem_to_reg $end
$var reg 1 2 mem_write_enable $end
$var reg 1 , reg_write_enable $end
$upscope $end
$scope module data_memory_inst $end
$var wire 1 # clk $end
$var wire 16 "" read_addr [15:0] $end
$var wire 16 #" read_data [15:0] $end
$var wire 1 $ reset $end
$var wire 16 $" write_addr [15:0] $end
$var wire 16 %" write_data [15:0] $end
$var wire 1 K write_enable $end
$upscope $end
$scope module forward_inst $end
$var wire 1 M ex_mem_reg_write_enable $end
$var wire 3 &" ex_mem_write_addr [2:0] $end
$var wire 3 '" id_ex_read_addr1 [2:0] $end
$var wire 3 (" id_ex_read_addr2 [2:0] $end
$var wire 1 c mem_wb_reg_write_enable $end
$var wire 3 )" mem_wb_write_addr [2:0] $end
$var reg 2 *" forward_a [1:0] $end
$var reg 2 +" forward_b [1:0] $end
$upscope $end
$scope module instruction_memory_inst $end
$var wire 16 ," instruction_out [15:0] $end
$var wire 16 -" address_in [15:0] $end
$upscope $end
$scope module pc $end
$var wire 1 F branch $end
$var wire 16 ." branch_addr [15:0] $end
$var wire 1 # clk $end
$var wire 1 & pc_write_enable $end
$var wire 1 $ reset $end
$var reg 16 /" pc_out [15:0] $end
$upscope $end
$scope module reg_file_inst $end
$var wire 1 # clk $end
$var wire 16 0" fib_out [15:0] $end
$var wire 3 1" read_addr1 [2:0] $end
$var wire 3 2" read_addr2 [2:0] $end
$var wire 3 3" write_addr [2:0] $end
$var wire 16 4" write_data [15:0] $end
$var wire 1 c write_enable $end
$var wire 16 5" read_data2 [15:0] $end
$var wire 16 6" read_data1 [15:0] $end
$scope begin $ivl_for_loop0 $end
$var integer 32 7" i [31:0] $end
$upscope $end
$upscope $end
$upscope $end
$upscope $end
$enddefinitions $end
$comment Show the parameter values. $end
$dumpall
b1010 ~
b1 }
b111 |
b101 {
b100 z
b11 y
b1011 x
b110 w
b1001 v
b1000 u
b10 t
b0 s
b110 o
b1 n
b101 m
b100 l
b11 k
b111 j
b10 i
b0 h
$end
#0
$dumpvars
b1000 7"
bx 6"
bx 5"
bx 4"
bx 3"
bx 2"
bx 1"
b0 0"
bx /"
bx ."
bx -"
bx ,"
b0 +"
b0 *"
bx )"
bx ("
bx '"
bx &"
bx %"
bx $"
bx #"
bx ""
b0 !"
bx r
bx q
bx p
bx g
bx f
bx e
bx d
xc
xb
bx a
bx `
bx _
bx ^
bx ]
x\
bx [
bx Z
bx Y
bx X
bx W
xV
xU
xT
bx S
xR
xQ
xP
bx O
bx N
xM
bx L
xK
xJ
xI
xH
bx G
xF
bx E
xD
bx C
bx B
b0 A
bx @
0?
0>
bx =
b0 <
b0 ;
b0 :
bx 9
08
bx 7
bx 6
05
bx 4
03
02
bx 1
bx 0
bx /
bx .
bx -
0,
bx +
bx *
x)
x(
bx '
x&
x%
1$
0#
b0 "
bx !
$end
#1
1)
b0 @
b0 p
b0 B
b0 g
1,
1&
b0 9
b0 C
b0 f
b0 4
b0 #"
b0 .
b0 6"
b0 -
b0 5"
b110001000000000 6
b110001000000000 ,"
b0 0
b0 1"
b0 /
b0 2"
b0 +
b0 7
b0 r
0%
0(
b0 $"
b0 ""
b0 !
b0 '
b0 *
b0 4"
b0 1
b0 -"
b0 /"
b0 _
b0 ^
b0 q
0P
b0 Y
b0 ("
b0 X
b0 '"
b0 =
b0 W
b0 S
b0 ]
0R
0Q
0U
0T
0V
0\
b0 O
b0 e
b0 [
b0 Z
b0 E
0H
0F
0J
0I
0K
0M
b0 N
b0 &"
b0 G
b0 ."
b0 L
b0 %"
0c
0b
b0 d
b0 )"
b0 3"
b0 a
b0 `
0D
1#
#2
0#
#3
1?
13
15
b1 +
b110 r
b110001000000000 ^
b110001000000000 q
1#
#4
0#
#5
b110001000000000 ^
b110001000000000 q
1#
#6
0#
#7
b110001000000000 ^
b110001000000000 q
1#
#8
0#
#9
b110001000000000 ^
b110001000000000 q
1#
#10
0#
#11
b110001000000000 ^
b110001000000000 q
1#
#12
0#
#13
b110001000000000 ^
b110001000000000 q
1#
#14
0#
#15
b110001000000000 ^
b110001000000000 q
1#
#16
0#
#17
b110001000000000 ^
b110001000000000 q
1#
#18
0#
#19
b110001000000000 ^
b110001000000000 q
1#
#20
0#
#21
b110001000000000 ^
b110001000000000 q
1#
#22
0#
#23
b110001000000000 ^
b110001000000000 q
1#
#24
0#
#25
b110001000000000 ^
b110001000000000 q
1#
#26
0#
#27
b110001000000000 ^
b110001000000000 q
1#
#28
0#
#29
b110001000000000 ^
b110001000000000 q
1#
#30
0#
#31
b110001000000000 ^
b110001000000000 q
1#
#32
0#
#33
b110001000000000 ^
b110001000000000 q
1#
#34
0#
#35
b110001000000000 ^
b110001000000000 q
1#
#36
0#
#37
b110001000000000 ^
b110001000000000 q
1#
#38
0#
#39
b110001000000000 ^
b110001000000000 q
1#
#40
0#
#41
b110001000000000 ^
b110001000000000 q
1#
#42
0#
#43
b110001000000000 ^
b110001000000000 q
1#
#44
0#
#45
b110001000000000 ^
b110001000000000 q
1#
#46
0#
#47
b110001000000000 ^
b110001000000000 q
1#
#48
0#
#49
b110001000000000 ^
b110001000000000 q
1#
#50
0#
#51
b110001000000000 ^
b110001000000000 q
1#
#52
0#
#53
b110001000000000 ^
b110001000000000 q
1#
#54
0#
#55
b110001000000000 ^
b110001000000000 q
1#
#56
0#
#57
b110001000000000 ^
b110001000000000 q
1#
#58
0#
#59
b110001000000000 ^
b110001000000000 q
1#
#60
0#
#61
b110001000000000 ^
b110001000000000 q
1#
#62
0#
#63
b110001000000000 ^
b110001000000000 q
1#
#64
0#
#65
b110001000000000 ^
b110001000000000 q
1#
#66
0#
#67
b110001000000000 ^
b110001000000000 q
1#
#68
0#
#69
b110001000000000 ^
b110001000000000 q
1#
#70
0#
#71
b110001000000000 ^
b110001000000000 q
1#
#72
0#
#73
b110001000000000 ^
b110001000000000 q
1#
#74
0#
#75
b110001000000000 ^
b110001000000000 q
1#
#76
0#
#77
b110001000000000 ^
b110001000000000 q
1#
#78
0#
#79
b110001000000000 ^
b110001000000000 q
1#
#80
0#
#81
b110001000000000 ^
b110001000000000 q
1#
#82
0#
#83
b110001000000000 ^
b110001000000000 q
1#
#84
0#
#85
b110001000000000 ^
b110001000000000 q
1#
#86
0#
#87
b110001000000000 ^
b110001000000000 q
1#
#88
0#
#89
b110001000000000 ^
b110001000000000 q
1#
#90
0#
#91
b110001000000000 ^
b110001000000000 q
1#
#92
0#
#93
b110001000000000 ^
b110001000000000 q
1#
#94
0#
#95
b110001000000000 ^
b110001000000000 q
1#
#96
0#
#97
b110001000000000 ^
b110001000000000 q
1#
#98
0#
#99
b110001000000000 ^
b110001000000000 q
1#
#100
0#
0$
#101
1&
b110010000000001 6
b110010000000001 ,"
0(
b1 1
b1 -"
b1 /"
1P
b1 ]
1U
1T
1\
1#
#102
0#
#103
b10 +
b1 7
b110000000000010 6
b110000000000010 ,"
1J
1I
1M
b1 N
b1 &"
b1 _
b110010000000001 ^
b110010000000001 q
b10 1
b10 -"
b10 /"
1#
#104
0#
#105
0)
b1 @
b1 p
b101001010000 6
b101001010000 ,"
b0 +
b10 7
b1 B
b1 g
b11 1
b11 -"
b11 /"
b10 _
b110000000000010 ^
b110000000000010 q
b1 W
b10 =
b1 S
b10 ]
1c
1b
b1 d
b1 )"
b1 3"
1#
#106
0#
